flutter_widget_mcp_server/__init__.py
flutter_widget_mcp_server/component_parser.py
flutter_widget_mcp_server/components.json
flutter_widget_mcp_server/gen_components_json.py
flutter_widget_mcp_server/loader.py
flutter_widget_mcp_server/main.py
flutter_widget_mcp_server/models.py
flutter_widget_mcp_server-0.1.15.dist-info/METADATA
flutter_widget_mcp_server-0.1.15.dist-info/WHEEL
flutter_widget_mcp_server-0.1.15.dist-info/entry_points.txt
flutter_widget_mcp_server-0.1.15.dist-info/top_level.txt
flutter_widget_mcp_server-0.1.15.dist-info/RECORD
