Metadata-Version: 2.4
Name: flutter_widget_mcp_server
Version: 0.1.15
Summary: Flutter Widget MCP Server for YL AI-enhanced Flutter component library
Author: anquan9494
Author-email: anquan9494@gmail.com
Requires-Python: >=3.7
Requires-Dist: fastapi<0.104.0,>=0.100.0
Requires-Dist: uvicorn==0.23.2
Requires-Dist: pydantic<3.0.0,>=2.0.0
Requires-Dist: fastapi-mcp<0.4.0,>=0.3.4
Requires-Dist: typing-extensions<5.0.0,>=4.8.0
Requires-Dist: anyio<5.0.0,>=3.7.1
Requires-Dist: mcp<2.0.0,>=1.10.1
Dynamic: author
Dynamic: author-email
Dynamic: description
Dynamic: description-content-type
Dynamic: requires-dist
Dynamic: requires-python
Dynamic: summary
